[
    {
        "id": "69451859ce2a6",
        "name": "reza",
        "email": "reza@gmail.com",
        "password": "$2y$12$hAgeMZaNv\/Ns1nHrde.YQeoTTqJeBySXXIOMT66GNurfzSUwbYW22"
    },
    {
        "id": "user_6684_0",
        "name": "Casey Rodriguez",
        "email": "casey.rodriguez0@example.com",
        "password": "$2y$10$NotARealHashJustDummyDataForNow"
    },
    {
        "id": "user_4221_1",
        "name": "Riley Smith",
        "email": "riley.smith1@example.com",
        "password": "$2y$10$NotARealHashJustDummyDataForNow"
    },
    {
        "id": "user_9608_2",
        "name": "Eden Miller",
        "email": "eden.miller2@example.com",
        "password": "$2y$10$NotARealHashJustDummyDataForNow"
    },
    {
        "id": "user_9678_3",
        "name": "Riley Williams",
        "email": "riley.williams3@example.com",
        "password": "$2y$10$NotARealHashJustDummyDataForNow"
    },
    {
        "id": "user_6859_4",
        "name": "Charlie Hernandez",
        "email": "charlie.hernandez4@example.com",
        "password": "$2y$10$NotARealHashJustDummyDataForNow"
    },
    {
        "id": "user_9554_5",
        "name": "Kai Garcia",
        "email": "kai.garcia5@example.com",
        "password": "$2y$10$NotARealHashJustDummyDataForNow"
    },
    {
        "id": "user_2988_6",
        "name": "Jordan Jones",
        "email": "jordan.jones6@example.com",
        "password": "$2y$10$NotARealHashJustDummyDataForNow"
    },
    {
        "id": "user_7656_7",
        "name": "Riley Williams",
        "email": "riley.williams7@example.com",
        "password": "$2y$10$NotARealHashJustDummyDataForNow"
    },
    {
        "id": "user_1970_8",
        "name": "Dakota Wilson",
        "email": "dakota.wilson8@example.com",
        "password": "$2y$10$NotARealHashJustDummyDataForNow"
    },
    {
        "id": "user_5059_9",
        "name": "Cameron Brown",
        "email": "cameron.brown9@example.com",
        "password": "$2y$10$NotARealHashJustDummyDataForNow"
    },
    {
        "id": "user_8000_10",
        "name": "Cameron Lopez",
        "email": "cameron.lopez10@example.com",
        "password": "$2y$10$NotARealHashJustDummyDataForNow"
    },
    {
        "id": "user_1238_11",
        "name": "Charlie Wilson",
        "email": "charlie.wilson11@example.com",
        "password": "$2y$10$NotARealHashJustDummyDataForNow"
    },
    {
        "id": "user_5290_12",
        "name": "Quinn Smith",
        "email": "quinn.smith12@example.com",
        "password": "$2y$10$NotARealHashJustDummyDataForNow"
    },
    {
        "id": "user_2482_13",
        "name": "Quinn Hernandez",
        "email": "quinn.hernandez13@example.com",
        "password": "$2y$10$NotARealHashJustDummyDataForNow"
    },
    {
        "id": "user_4497_14",
        "name": "Casey Davis",
        "email": "casey.davis14@example.com",
        "password": "$2y$10$NotARealHashJustDummyDataForNow"
    },
    {
        "id": "user_9910_15",
        "name": "Cameron Lopez",
        "email": "cameron.lopez15@example.com",
        "password": "$2y$10$NotARealHashJustDummyDataForNow"
    },
    {
        "id": "user_6978_16",
        "name": "Charlie Davis",
        "email": "charlie.davis16@example.com",
        "password": "$2y$10$NotARealHashJustDummyDataForNow"
    },
    {
        "id": "user_3145_17",
        "name": "Dakota Wilson",
        "email": "dakota.wilson17@example.com",
        "password": "$2y$10$NotARealHashJustDummyDataForNow"
    },
    {
        "id": "user_6833_18",
        "name": "Kai Smith",
        "email": "kai.smith18@example.com",
        "password": "$2y$10$NotARealHashJustDummyDataForNow"
    },
    {
        "id": "user_5439_19",
        "name": "Cameron Miller",
        "email": "cameron.miller19@example.com",
        "password": "$2y$10$NotARealHashJustDummyDataForNow"
    },
    {
        "id": "user_5148_20",
        "name": "Alex Lopez",
        "email": "alex.lopez20@example.com",
        "password": "$2y$10$NotARealHashJustDummyDataForNow"
    },
    {
        "id": "user_2019_21",
        "name": "Avery Lopez",
        "email": "avery.lopez21@example.com",
        "password": "$2y$10$NotARealHashJustDummyDataForNow"
    },
    {
        "id": "user_3952_22",
        "name": "Casey Davis",
        "email": "casey.davis22@example.com",
        "password": "$2y$10$NotARealHashJustDummyDataForNow"
    },
    {
        "id": "user_8577_23",
        "name": "Avery Johnson",
        "email": "avery.johnson23@example.com",
        "password": "$2y$10$NotARealHashJustDummyDataForNow"
    },
    {
        "id": "user_2919_24",
        "name": "Sam Smith",
        "email": "sam.smith24@example.com",
        "password": "$2y$10$NotARealHashJustDummyDataForNow"
    },
    {
        "id": "user_4624_25",
        "name": "Reese Rodriguez",
        "email": "reese.rodriguez25@example.com",
        "password": "$2y$10$NotARealHashJustDummyDataForNow"
    },
    {
        "id": "user_7618_26",
        "name": "Jamie Martinez",
        "email": "jamie.martinez26@example.com",
        "password": "$2y$10$NotARealHashJustDummyDataForNow"
    },
    {
        "id": "user_1657_27",
        "name": "Dakota Martinez",
        "email": "dakota.martinez27@example.com",
        "password": "$2y$10$NotARealHashJustDummyDataForNow"
    },
    {
        "id": "user_5140_28",
        "name": "Quinn Gonzalez",
        "email": "quinn.gonzalez28@example.com",
        "password": "$2y$10$NotARealHashJustDummyDataForNow"
    },
    {
        "id": "user_2302_29",
        "name": "Taylor Jones",
        "email": "taylor.jones29@example.com",
        "password": "$2y$10$NotARealHashJustDummyDataForNow"
    },
    {
        "id": "user_5079_30",
        "name": "Kai Lopez",
        "email": "kai.lopez30@example.com",
        "password": "$2y$10$NotARealHashJustDummyDataForNow"
    },
    {
        "id": "user_2194_31",
        "name": "Kai Hernandez",
        "email": "kai.hernandez31@example.com",
        "password": "$2y$10$NotARealHashJustDummyDataForNow"
    },
    {
        "id": "user_9358_32",
        "name": "Jamie Smith",
        "email": "jamie.smith32@example.com",
        "password": "$2y$10$NotARealHashJustDummyDataForNow"
    },
    {
        "id": "user_8941_33",
        "name": "Avery Jones",
        "email": "avery.jones33@example.com",
        "password": "$2y$10$NotARealHashJustDummyDataForNow"
    },
    {
        "id": "user_9674_34",
        "name": "Charlie Rodriguez",
        "email": "charlie.rodriguez34@example.com",
        "password": "$2y$10$NotARealHashJustDummyDataForNow"
    },
    {
        "id": "user_1045_35",
        "name": "Alex Williams",
        "email": "alex.williams35@example.com",
        "password": "$2y$10$NotARealHashJustDummyDataForNow"
    },
    {
        "id": "user_7275_36",
        "name": "Sam Hernandez",
        "email": "sam.hernandez36@example.com",
        "password": "$2y$10$NotARealHashJustDummyDataForNow"
    },
    {
        "id": "user_2233_37",
        "name": "Sam Hernandez",
        "email": "sam.hernandez37@example.com",
        "password": "$2y$10$NotARealHashJustDummyDataForNow"
    },
    {
        "id": "user_6289_38",
        "name": "Charlie Martinez",
        "email": "charlie.martinez38@example.com",
        "password": "$2y$10$NotARealHashJustDummyDataForNow"
    },
    {
        "id": "user_3682_39",
        "name": "Jamie Jones",
        "email": "jamie.jones39@example.com",
        "password": "$2y$10$NotARealHashJustDummyDataForNow"
    },
    {
        "id": "user_2589_40",
        "name": "Riley Brown",
        "email": "riley.brown40@example.com",
        "password": "$2y$10$NotARealHashJustDummyDataForNow"
    },
    {
        "id": "user_8011_41",
        "name": "Cameron Smith",
        "email": "cameron.smith41@example.com",
        "password": "$2y$10$NotARealHashJustDummyDataForNow"
    },
    {
        "id": "user_3651_42",
        "name": "Quinn Garcia",
        "email": "quinn.garcia42@example.com",
        "password": "$2y$10$NotARealHashJustDummyDataForNow"
    },
    {
        "id": "user_8327_43",
        "name": "Riley Jones",
        "email": "riley.jones43@example.com",
        "password": "$2y$10$NotARealHashJustDummyDataForNow"
    },
    {
        "id": "user_2275_44",
        "name": "Alex Rodriguez",
        "email": "alex.rodriguez44@example.com",
        "password": "$2y$10$NotARealHashJustDummyDataForNow"
    },
    {
        "id": "user_1323_45",
        "name": "Morgan Lopez",
        "email": "morgan.lopez45@example.com",
        "password": "$2y$10$NotARealHashJustDummyDataForNow"
    },
    {
        "id": "user_5874_46",
        "name": "Quinn Smith",
        "email": "quinn.smith46@example.com",
        "password": "$2y$10$NotARealHashJustDummyDataForNow"
    },
    {
        "id": "user_6957_47",
        "name": "Riley Smith",
        "email": "riley.smith47@example.com",
        "password": "$2y$10$NotARealHashJustDummyDataForNow"
    },
    {
        "id": "user_5095_48",
        "name": "Riley Lopez",
        "email": "riley.lopez48@example.com",
        "password": "$2y$10$NotARealHashJustDummyDataForNow"
    },
    {
        "id": "user_9325_49",
        "name": "Kai Lopez",
        "email": "kai.lopez49@example.com",
        "password": "$2y$10$NotARealHashJustDummyDataForNow"
    },
    {
        "id": "user_reza_demo",
        "name": "Reza",
        "email": "reza@sneakeazy.com",
        "password": "$2y$12$wy3gD3P353GgBWyjAA7gPuduz9y4.LQ8X5sK4kvRIaMiPkdXzgOF6"
    },
    {
        "id": "69451b59a0783",
        "name": "salomon",
        "email": "salomon@gmail.com",
        "password": "$2y$12$gVXF8q2aOiFb3ngIK1ju4OT7Pvj94BpptPsNuVqUi.f2o\/tXK8dt2"
    },
    {
        "id": "69452165f1224",
        "name": "asics",
        "email": "asics@gmail.com",
        "password": "$2y$12$NuFdMYbYkHE5dQSQ5DzIkeudbreU14xHG1eau396RwjW6UspeUdB2"
    },
    {
        "id": "6949656c6e2b0",
        "name": "user2",
        "email": "user2@gmail.com",
        "password": "$2y$12$weOcAUYLE9P440MLF0NZp.W1jJaAxHpp1fZq2sy5fhXPwzED5Qgs2"
    },
    {
        "id": "6949eb357ae76",
        "name": "usera",
        "email": "usera@gmail.com",
        "password": "$2y$12$svUQnpXZwV11gRdl8Ubmcehltgjm9kbkvE2aLBNi0ZpclfSXfUe9S"
    }
]